LICENSE
MANIFEST.in
README.rst
requirements.txt
setup.py
docs/Makefile
docs/api.rst
docs/conf.py
docs/guide.rst
docs/index.rst
docs/tutorial.rst
docs/_build/html/_sources/api.rst.txt
docs/_build/html/_sources/guide.rst.txt
docs/_build/html/_sources/index.rst.txt
docs/_build/html/_sources/tutorial.rst.txt
docs/_build/html/_static/comment-bright.png
docs/_build/html/_static/comment-close.png
docs/_build/html/_static/comment.png
docs/_build/html/_static/down-pressed.png
docs/_build/html/_static/down.png
docs/_build/html/_static/file.png
docs/_build/html/_static/minus.png
docs/_build/html/_static/plus.png
docs/_build/html/_static/up-pressed.png
docs/_build/html/_static/up.png
docs/_build/html/_static/fonts/fontawesome-webfont.svg
jpredapi/__init__.py
jpredapi/__main__.py
jpredapi/api.py
jpredapi/cli.py
jpredapi.egg-info/PKG-INFO
jpredapi.egg-info/SOURCES.txt
jpredapi.egg-info/dependency_links.txt
jpredapi.egg-info/entry_points.txt
jpredapi.egg-info/requires.txt
jpredapi.egg-info/top_level.txt