Metadata-Version: 1.1
Name: jpredapi
Version: 1.5.3
Summary: Python library for submitting jobs to JPRED - A Protein Secondary Structure Prediction Server
Home-page: https://github.com/MoseleyBioinformaticsLab/jpredapi
Author: Andrey Smelter
Author-email: andrey.smelter@gmail.com
License: BSD
Keywords: JPRED REST API
Platform: any
Classifier: Development Status :: 4 - Beta
Classifier: Environment :: Console
Classifier: Intended Audience :: Developers
Classifier: Intended Audience :: Science/Research
Classifier: License :: OSI Approved :: BSD License
Classifier: Operating System :: OS Independent
Classifier: Programming Language :: Python :: 2.7
Classifier: Programming Language :: Python :: 3.4
Classifier: Programming Language :: Python :: 3.5
Classifier: Programming Language :: Python :: 3.6
Classifier: Programming Language :: Python :: 3.7
Classifier: Topic :: Scientific/Engineering :: Bio-Informatics
Classifier: Topic :: Software Development :: Libraries :: Python Modules
